py_snappy/__init__.py
py_snappy/constants.py
py_snappy/exceptions.py
py_snappy/main.py
py_snappy-0.1.0a1.dist-info/LICENSE
py_snappy-0.1.0a1.dist-info/METADATA
py_snappy-0.1.0a1.dist-info/WHEEL
py_snappy-0.1.0a1.dist-info/top_level.txt
py_snappy-0.1.0a1.dist-info/RECORD
