Metadata-Version: 2.1
Name: py-snappy
Version: 0.1.0a1
Summary: py-snappy: A pure python implementation of the Snappy compression algorithm
Home-page: https://github.com/ethereum/py-snappy
Author: Jason Carver
Author-email: ethcalibur+pip@gmail.com
License: MIT
Keywords: ethereum
Platform: UNKNOWN
Classifier: Development Status :: 3 - Alpha
Classifier: Intended Audience :: Developers
Classifier: License :: OSI Approved :: MIT License
Classifier: Natural Language :: English
Classifier: Programming Language :: Python :: 3
Classifier: Programming Language :: Python :: 3.6
Classifier: Programming Language :: Python :: 3.7
Classifier: Programming Language :: Python :: Implementation :: PyPy
Requires-Python: >=3.6, <4
Provides-Extra: dev
Requires-Dist: bumpversion (<1,>=0.5.3); extra == 'dev'
Requires-Dist: pytest-watch (<5,>=4.1.0); extra == 'dev'
Requires-Dist: wheel; extra == 'dev'
Requires-Dist: twine; extra == 'dev'
Requires-Dist: ipython; extra == 'dev'
Requires-Dist: pytest (>=3.6.0); extra == 'dev'
Requires-Dist: pytest-xdist; extra == 'dev'
Requires-Dist: tox (<3,>=2.9.1); extra == 'dev'
Requires-Dist: hypothesis (==3.74.3); extra == 'dev'
Requires-Dist: python-snappy (<1,>=0.5.3); extra == 'dev'
Requires-Dist: flake8 (==3.4.1); extra == 'dev'
Requires-Dist: black (==18.9b0); extra == 'dev'
Requires-Dist: mypy (==0.630); extra == 'dev'
Requires-Dist: Sphinx (<2,>=1.6.5); extra == 'dev'
Requires-Dist: sphinx-rtd-theme (>=0.1.9); extra == 'dev'
Provides-Extra: doc
Requires-Dist: Sphinx (<2,>=1.6.5); extra == 'doc'
Requires-Dist: sphinx-rtd-theme (>=0.1.9); extra == 'doc'
Provides-Extra: lint
Requires-Dist: flake8 (==3.4.1); extra == 'lint'
Requires-Dist: black (==18.9b0); extra == 'lint'
Requires-Dist: mypy (==0.630); extra == 'lint'
Provides-Extra: test
Requires-Dist: pytest (>=3.6.0); extra == 'test'
Requires-Dist: pytest-xdist; extra == 'test'
Requires-Dist: tox (<3,>=2.9.1); extra == 'test'
Requires-Dist: hypothesis (==3.74.3); extra == 'test'
Requires-Dist: python-snappy (<1,>=0.5.3); extra == 'test'
